{
  "environment": "outdoors",
  "description": "The hallowed grounds of Miskatonic University, where Gothic spires pierce the sky and ancient knowledge lurks in the restricted sections of the library. The campus is a maze of ivy-covered buildings, each containing secrets that would drive lesser minds to madness.",
  "special_rules": {
    "sanity_drain_rate": 0.08,
    "npc_spawn_modifier": 1.1,
    "combat_modifier": 0.7,
    "exploration_bonus": 1.3,
    "access_requirements": ["student_id", "faculty_credentials"]
  }
}
