{"nodes": [{"id": "c_projects_mythosmud_server_api_professions_py", "label": "professions.py", "file_type": "code", "source_file": "server/api/professions.py", "source_location": "L1"}, {"id": "api_professions_get_all_professions", "label": "get_all_professions()", "file_type": "code", "source_file": "server/api/professions.py", "source_location": "L26"}, {"id": "request", "label": "Request", "file_type": "code", "source_file": "server/api/professions.py", "source_location": "L26"}, {"id": "user", "label": "User", "file_type": "code", "source_file": "server/api/professions.py", "source_location": "L26"}, {"id": "professionservice", "label": "ProfessionService", "file_type": "code", "source_file": "server/api/professions.py", "source_location": "L26"}, {"id": "professionlistresponse", "label": "ProfessionListResponse", "file_type": "code", "source_file": "server/api/professions.py", "source_location": "L26"}, {"id": "api_professions_get_profession_by_id", "label": "get_profession_by_id()", "file_type": "code", "source_file": "server/api/professions.py", "source_location": "L64"}, {"id": "professionresponse", "label": "ProfessionResponse", "file_type": "code", "source_file": "server/api/professions.py", "source_location": "L64"}, {"id": "api_professions_rationale_1", "label": "Profession management API endpoints for MythosMUD server.  This module handles a", "file_type": "rationale", "source_file": "server/api/professions.py", "source_location": "L1"}, {"id": "api_professions_rationale_31", "label": "Retrieve all available professions for character creation with caching.      :pa", "file_type": "rationale", "source_file": "server/api/professions.py", "source_location": "L31"}, {"id": "api_professions_rationale_70", "label": "Retrieve specific profession details by ID with caching.      :param profession_", "file_type": "rationale", "source_file": "server/api/professions.py", "source_location": "L70"}], "edges": [{"source": "c_projects_mythosmud_server_api_professions_py", "target": "fastapi", "relation": "imports_from", "context": "import", "confidence": "EXTRACTED", "source_file": "server/api/professions.py", "source_location": "L8", "weight": 1.0}, {"source": "c_projects_mythosmud_server_api_professions_py", "target": "c_projects_mythosmud_server_auth_users_py", "relation": "imports_from", "context": "import", "confidence": "EXTRACTED", "source_file": "server/api/professions.py", "source_location": "L10", "weight": 1.0}, {"source": "c_projects_mythosmud_server_api_professions_py", "target": "c_projects_mythosmud_server_dependencies_py", "relation": "imports_from", "context": "import", "confidence": "EXTRACTED", "source_file": "server/api/professions.py", "source_location": "L11", "weight": 1.0}, {"source": "c_projects_mythosmud_server_api_professions_py", "target": "c_projects_mythosmud_server_error_types_py", "relation": "imports_from", "context": "import", "confidence": "EXTRACTED", "source_file": "server/api/professions.py", "source_location": "L12", "weight": 1.0}, {"source": "c_projects_mythosmud_server_api_professions_py", "target": "c_projects_mythosmud_server_exceptions_py", "relation": "imports_from", "context": "import", "confidence": "EXTRACTED", "source_file": "server/api/professions.py", "source_location": "L13", "weight": 1.0}, {"source": "c_projects_mythosmud_server_api_professions_py", "target": "c_projects_mythosmud_server_game_profession_service_py", "relation": "imports_from", "context": "import", "confidence": "EXTRACTED", "source_file": "server/api/professions.py", "source_location": "L14", "weight": 1.0}, {"source": "c_projects_mythosmud_server_api_professions_py", "target": "c_projects_mythosmud_server_models_user_py", "relation": "imports_from", "context": "import", "confidence": "EXTRACTED", "source_file": "server/api/professions.py", "source_location": "L15", "weight": 1.0}, {"source": "c_projects_mythosmud_server_api_professions_py", "target": "c_projects_mythosmud_server_schemas_players_py", "relation": "imports_from", "context": "import", "confidence": "EXTRACTED", "source_file": "server/api/professions.py", "source_location": "L16", "weight": 1.0}, {"source": "c_projects_mythosmud_server_api_professions_py", "target": "c_projects_mythosmud_server_structured_logging_enhanced_logging_config_py", "relation": "imports_from", "context": "import", "confidence": "EXTRACTED", "source_file": "server/api/professions.py", "source_location": "L17", "weight": 1.0}, {"source": "c_projects_mythosmud_server_api_professions_py", "target": "api_professions_get_all_professions", "relation": "contains", "confidence": "EXTRACTED", "source_file": "server/api/professions.py", "source_location": "L26", "weight": 1.0}, {"source": "api_professions_get_all_professions", "target": "request", "relation": "references", "context": "parameter_type", "confidence": "EXTRACTED", "source_file": "server/api/professions.py", "source_location": "L26", "weight": 1.0}, {"source": "api_professions_get_all_professions", "target": "user", "relation": "references", "context": "parameter_type", "confidence": "EXTRACTED", "source_file": "server/api/professions.py", "source_location": "L26", "weight": 1.0}, {"source": "api_professions_get_all_professions", "target": "professionservice", "relation": "references", "context": "parameter_type", "confidence": "EXTRACTED", "source_file": "server/api/professions.py", "source_location": "L26", "weight": 1.0}, {"source": "api_professions_get_all_professions", "target": "professionlistresponse", "relation": "references", "context": "return_type", "confidence": "EXTRACTED", "source_file": "server/api/professions.py", "source_location": "L26", "weight": 1.0}, {"source": "c_projects_mythosmud_server_api_professions_py", "target": "api_professions_get_profession_by_id", "relation": "contains", "confidence": "EXTRACTED", "source_file": "server/api/professions.py", "source_location": "L64", "weight": 1.0}, {"source": "api_professions_get_profession_by_id", "target": "request", "relation": "references", "context": "parameter_type", "confidence": "EXTRACTED", "source_file": "server/api/professions.py", "source_location": "L64", "weight": 1.0}, {"source": "api_professions_get_profession_by_id", "target": "user", "relation": "references", "context": "parameter_type", "confidence": "EXTRACTED", "source_file": "server/api/professions.py", "source_location": "L64", "weight": 1.0}, {"source": "api_professions_get_profession_by_id", "target": "professionservice", "relation": "references", "context": "parameter_type", "confidence": "EXTRACTED", "source_file": "server/api/professions.py", "source_location": "L64", "weight": 1.0}, {"source": "api_professions_get_profession_by_id", "target": "professionresponse", "relation": "references", "context": "return_type", "confidence": "EXTRACTED", "source_file": "server/api/professions.py", "source_location": "L64", "weight": 1.0}, {"source": "api_professions_get_all_professions", "target": "professionlistresponse", "relation": "calls", "context": "call", "confidence": "EXTRACTED", "source_file": "server/api/professions.py", "source_location": "L50", "weight": 1.0}, {"source": "api_professions_get_profession_by_id", "target": "professionresponse", "relation": "calls", "context": "call", "confidence": "EXTRACTED", "source_file": "server/api/professions.py", "source_location": "L99", "weight": 1.0}, {"source": "api_professions_rationale_1", "target": "c_projects_mythosmud_server_api_professions_py", "relation": "rationale_for", "confidence": "EXTRACTED", "source_file": "server/api/professions.py", "source_location": "L1", "weight": 1.0}, {"source": "api_professions_rationale_31", "target": "api_professions_get_all_professions", "relation": "rationale_for", "confidence": "EXTRACTED", "source_file": "server/api/professions.py", "source_location": "L31", "weight": 1.0}, {"source": "api_professions_rationale_70", "target": "api_professions_get_profession_by_id", "relation": "rationale_for", "confidence": "EXTRACTED", "source_file": "server/api/professions.py", "source_location": "L70", "weight": 1.0}], "raw_calls": [{"caller_nid": "api_professions_get_all_professions", "callee": "LoggedHTTPException", "is_member_call": false, "source_file": "C:\\projects\\MythosMUD\\server\\api\\professions.py", "source_location": "L41"}, {"caller_nid": "api_professions_get_all_professions", "callee": "get_all_professions_dict", "is_member_call": true, "source_file": "C:\\projects\\MythosMUD\\server\\api\\professions.py", "source_location": "L49"}, {"caller_nid": "api_professions_get_all_professions", "callee": "error", "is_member_call": true, "source_file": "C:\\projects\\MythosMUD\\server\\api\\professions.py", "source_location": "L54"}, {"caller_nid": "api_professions_get_all_professions", "callee": "LoggedHTTPException", "is_member_call": false, "source_file": "C:\\projects\\MythosMUD\\server\\api\\professions.py", "source_location": "L55"}, {"caller_nid": "api_professions_get_profession_by_id", "callee": "LoggedHTTPException", "is_member_call": false, "source_file": "C:\\projects\\MythosMUD\\server\\api\\professions.py", "source_location": "L81"}, {"caller_nid": "api_professions_get_profession_by_id", "callee": "get_profession_by_id_dict", "is_member_call": true, "source_file": "C:\\projects\\MythosMUD\\server\\api\\professions.py", "source_location": "L89"}, {"caller_nid": "api_professions_get_profession_by_id", "callee": "LoggedHTTPException", "is_member_call": false, "source_file": "C:\\projects\\MythosMUD\\server\\api\\professions.py", "source_location": "L92"}, {"caller_nid": "api_professions_get_profession_by_id", "callee": "error", "is_member_call": true, "source_file": "C:\\projects\\MythosMUD\\server\\api\\professions.py", "source_location": "L105"}, {"caller_nid": "api_professions_get_profession_by_id", "callee": "LoggedHTTPException", "is_member_call": false, "source_file": "C:\\projects\\MythosMUD\\server\\api\\professions.py", "source_location": "L106"}]}
