{"nodes": [{"id": "c_projects_mythosmud_docs_examples_logging_readme_md", "label": "README.md", "file_type": "document", "source_file": "docs/examples/logging/README.md", "source_location": "L1"}, {"id": "logging_readme_enhanced_logging_examples", "label": "Enhanced Logging Examples", "file_type": "document", "source_file": "docs/examples/logging/README.md", "source_location": "L1"}, {"id": "logging_readme_files_overview", "label": "Files Overview", "file_type": "document", "source_file": "docs/examples/logging/README.md", "source_location": "L5"}, {"id": "logging_readme_correct_patterns_py", "label": "`correct_patterns.py`", "file_type": "document", "source_file": "docs/examples/logging/README.md", "source_location": "L7"}, {"id": "logging_readme_deprecated_patterns_py", "label": "`deprecated_patterns.py`", "file_type": "document", "source_file": "docs/examples/logging/README.md", "source_location": "L24"}, {"id": "logging_readme_migration_examples_py", "label": "`migration_examples.py`", "file_type": "document", "source_file": "docs/examples/logging/README.md", "source_location": "L38"}, {"id": "logging_readme_fastapi_integration_py", "label": "`fastapi_integration.py`", "file_type": "document", "source_file": "docs/examples/logging/README.md", "source_location": "L58"}, {"id": "logging_readme_websocket_integration_py", "label": "`websocket_integration.py`", "file_type": "document", "source_file": "docs/examples/logging/README.md", "source_location": "L73"}, {"id": "logging_readme_testing_examples_py", "label": "`testing_examples.py`", "file_type": "document", "source_file": "docs/examples/logging/README.md", "source_location": "L87"}, {"id": "logging_readme_usage_guidelines", "label": "Usage Guidelines", "file_type": "document", "source_file": "docs/examples/logging/README.md", "source_location": "L108"}, {"id": "logging_readme_for_developers", "label": "For Developers", "file_type": "document", "source_file": "docs/examples/logging/README.md", "source_location": "L110"}, {"id": "logging_readme_for_code_reviews", "label": "For Code Reviews", "file_type": "document", "source_file": "docs/examples/logging/README.md", "source_location": "L119"}, {"id": "logging_readme_for_ai_agents", "label": "For AI Agents", "file_type": "document", "source_file": "docs/examples/logging/README.md", "source_location": "L129"}, {"id": "logging_readme_key_principles", "label": "Key Principles", "file_type": "document", "source_file": "docs/examples/logging/README.md", "source_location": "L137"}, {"id": "logging_readme_do", "label": "\u2705 DO", "file_type": "document", "source_file": "docs/examples/logging/README.md", "source_location": "L139"}, {"id": "logging_readme_don_t", "label": "\u274c DON'T", "file_type": "document", "source_file": "docs/examples/logging/README.md", "source_location": "L151"}, {"id": "logging_readme_documentation_references", "label": "Documentation References", "file_type": "document", "source_file": "docs/examples/logging/README.md", "source_location": "L163"}, {"id": "logging_readme_examples_usage", "label": "Examples Usage", "file_type": "document", "source_file": "docs/examples/logging/README.md", "source_location": "L173"}], "edges": [{"source": "c_projects_mythosmud_docs_examples_logging_readme_md", "target": "logging_readme_enhanced_logging_examples", "relation": "contains", "confidence": "EXTRACTED", "source_file": "docs/examples/logging/README.md", "source_location": "L1", "weight": 1.0}, {"source": "logging_readme_enhanced_logging_examples", "target": "logging_readme_files_overview", "relation": "contains", "confidence": "EXTRACTED", "source_file": "docs/examples/logging/README.md", "source_location": "L5", "weight": 1.0}, {"source": "logging_readme_files_overview", "target": "logging_readme_correct_patterns_py", "relation": "contains", "confidence": "EXTRACTED", "source_file": "docs/examples/logging/README.md", "source_location": "L7", "weight": 1.0}, {"source": "logging_readme_files_overview", "target": "logging_readme_deprecated_patterns_py", "relation": "contains", "confidence": "EXTRACTED", "source_file": "docs/examples/logging/README.md", "source_location": "L24", "weight": 1.0}, {"source": "logging_readme_files_overview", "target": "logging_readme_migration_examples_py", "relation": "contains", "confidence": "EXTRACTED", "source_file": "docs/examples/logging/README.md", "source_location": "L38", "weight": 1.0}, {"source": "logging_readme_files_overview", "target": "logging_readme_fastapi_integration_py", "relation": "contains", "confidence": "EXTRACTED", "source_file": "docs/examples/logging/README.md", "source_location": "L58", "weight": 1.0}, {"source": "logging_readme_files_overview", "target": "logging_readme_websocket_integration_py", "relation": "contains", "confidence": "EXTRACTED", "source_file": "docs/examples/logging/README.md", "source_location": "L73", "weight": 1.0}, {"source": "logging_readme_files_overview", "target": "logging_readme_testing_examples_py", "relation": "contains", "confidence": "EXTRACTED", "source_file": "docs/examples/logging/README.md", "source_location": "L87", "weight": 1.0}, {"source": "logging_readme_enhanced_logging_examples", "target": "logging_readme_usage_guidelines", "relation": "contains", "confidence": "EXTRACTED", "source_file": "docs/examples/logging/README.md", "source_location": "L108", "weight": 1.0}, {"source": "logging_readme_usage_guidelines", "target": "logging_readme_for_developers", "relation": "contains", "confidence": "EXTRACTED", "source_file": "docs/examples/logging/README.md", "source_location": "L110", "weight": 1.0}, {"source": "logging_readme_usage_guidelines", "target": "logging_readme_for_code_reviews", "relation": "contains", "confidence": "EXTRACTED", "source_file": "docs/examples/logging/README.md", "source_location": "L119", "weight": 1.0}, {"source": "logging_readme_usage_guidelines", "target": "logging_readme_for_ai_agents", "relation": "contains", "confidence": "EXTRACTED", "source_file": "docs/examples/logging/README.md", "source_location": "L129", "weight": 1.0}, {"source": "logging_readme_enhanced_logging_examples", "target": "logging_readme_key_principles", "relation": "contains", "confidence": "EXTRACTED", "source_file": "docs/examples/logging/README.md", "source_location": "L137", "weight": 1.0}, {"source": "logging_readme_key_principles", "target": "logging_readme_do", "relation": "contains", "confidence": "EXTRACTED", "source_file": "docs/examples/logging/README.md", "source_location": "L139", "weight": 1.0}, {"source": "logging_readme_key_principles", "target": "logging_readme_don_t", "relation": "contains", "confidence": "EXTRACTED", "source_file": "docs/examples/logging/README.md", "source_location": "L151", "weight": 1.0}, {"source": "logging_readme_enhanced_logging_examples", "target": "logging_readme_documentation_references", "relation": "contains", "confidence": "EXTRACTED", "source_file": "docs/examples/logging/README.md", "source_location": "L163", "weight": 1.0}, {"source": "logging_readme_enhanced_logging_examples", "target": "logging_readme_examples_usage", "relation": "contains", "confidence": "EXTRACTED", "source_file": "docs/examples/logging/README.md", "source_location": "L173", "weight": 1.0}], "input_tokens": 0, "output_tokens": 0}
