{"nodes": [{"id": "c_projects_mythosmud_server_game_movement_service_py", "label": "movement_service.py", "file_type": "code", "source_file": "server/game/movement_service.py", "source_location": "L1"}, {"id": "game_movement_service_movementservice", "label": "MovementService", "file_type": "code", "source_file": "server/game/movement_service.py", "source_location": "L35"}, {"id": "game_movement_service_movementservice_init", "label": ".__init__()", "file_type": "code", "source_file": "server/game/movement_service.py", "source_location": "L48"}, {"id": "eventbus", "label": "EventBus", "file_type": "code", "source_file": "server/game/movement_service.py", "source_location": "L48"}, {"id": "any", "label": "Any", "file_type": "code", "source_file": "server/game/movement_service.py", "source_location": "L48"}, {"id": "game_movement_service_movementservice_set_player_combat_service", "label": ".set_player_combat_service()", "file_type": "code", "source_file": "server/game/movement_service.py", "source_location": "L82"}, {"id": "game_movement_service_movementservice_validate_move_params", "label": "._validate_move_params()", "file_type": "code", "source_file": "server/game/movement_service.py", "source_location": "L98"}, {"id": "uuid", "label": "UUID", "file_type": "code", "source_file": "server/game/movement_service.py", "source_location": "L98"}, {"id": "game_movement_service_movementservice_resolve_player_for_movement", "label": "._resolve_player_for_movement()", "file_type": "code", "source_file": "server/game/movement_service.py", "source_location": "L136"}, {"id": "game_movement_service_movementservice_get_rooms_for_movement", "label": "._get_rooms_for_movement()", "file_type": "code", "source_file": "server/game/movement_service.py", "source_location": "L171"}, {"id": "room", "label": "Room", "file_type": "code", "source_file": "server/game/movement_service.py", "source_location": "L171"}, {"id": "game_movement_service_movementservice_execute_room_transfer", "label": "._execute_room_transfer()", "file_type": "code", "source_file": "server/game/movement_service.py", "source_location": "L199"}, {"id": "game_movement_service_movementservice_persist_player_location", "label": "._persist_player_location()", "file_type": "code", "source_file": "server/game/movement_service.py", "source_location": "L212"}, {"id": "game_movement_service_movementservice_handle_tutorial_exit_if_applicable", "label": "._handle_tutorial_exit_if_applicable()", "file_type": "code", "source_file": "server/game/movement_service.py", "source_location": "L221"}, {"id": "game_movement_service_movementservice_mark_room_explored", "label": "._mark_room_explored()", "file_type": "code", "source_file": "server/game/movement_service.py", "source_location": "L240"}, {"id": "game_movement_service_movementservice_handle_movement_error", "label": "._handle_movement_error()", "file_type": "code", "source_file": "server/game/movement_service.py", "source_location": "L258"}, {"id": "exception", "label": "Exception", "file_type": "code", "source_file": "server/game/movement_service.py", "source_location": "L258"}, {"id": "game_movement_service_movementservice_move_player", "label": ".move_player()", "file_type": "code", "source_file": "server/game/movement_service.py", "source_location": "L295"}, {"id": "game_movement_service_movementservice_extract_player_id", "label": "._extract_player_id()", "file_type": "code", "source_file": "server/game/movement_service.py", "source_location": "L388"}, {"id": "game_movement_service_movementservice_check_combat_state", "label": "._check_combat_state()", "file_type": "code", "source_file": "server/game/movement_service.py", "source_location": "L415"}, {"id": "game_movement_service_movementservice_check_player_posture", "label": "._check_player_posture()", "file_type": "code", "source_file": "server/game/movement_service.py", "source_location": "L441"}, {"id": "game_movement_service_movementservice_validate_player_room_membership", "label": "._validate_player_room_membership()", "file_type": "code", "source_file": "server/game/movement_service.py", "source_location": "L474"}, {"id": "game_movement_service_movementservice_validate_movement", "label": "._validate_movement()", "file_type": "code", "source_file": "server/game/movement_service.py", "source_location": "L510"}, {"id": "game_movement_service_movementservice_validate_exit", "label": "._validate_exit()", "file_type": "code", "source_file": "server/game/movement_service.py", "source_location": "L574"}, {"id": "game_movement_service_movementservice_add_player_to_room", "label": ".add_player_to_room()", "file_type": "code", "source_file": "server/game/movement_service.py", "source_location": "L620"}, {"id": "game_movement_service_movementservice_validate_remove_player_params", "label": "._validate_remove_player_params()", "file_type": "code", "source_file": "server/game/movement_service.py", "source_location": "L701"}, {"id": "game_movement_service_movementservice_remove_player_from_room", "label": ".remove_player_from_room()", "file_type": "code", "source_file": "server/game/movement_service.py", "source_location": "L722"}, {"id": "game_movement_service_movementservice_get_player_room", "label": ".get_player_room()", "file_type": "code", "source_file": "server/game/movement_service.py", "source_location": "L767"}, {"id": "game_movement_service_movementservice_get_room_players", "label": ".get_room_players()", "file_type": "code", "source_file": "server/game/movement_service.py", "source_location": "L805"}, {"id": "game_movement_service_movementservice_validate_player_location", "label": ".validate_player_location()", "file_type": "code", "source_file": "server/game/movement_service.py", "source_location": "L829"}, {"id": "game_movement_service_rationale_1", "label": "Movement service for MythosMUD.  This module provides the MovementService class", "file_type": "rationale", "source_file": "server/game/movement_service.py", "source_location": "L1"}, {"id": "game_movement_service_rationale_36", "label": "Service for handling atomic player movement operations.      This class provides", "file_type": "rationale", "source_file": "server/game/movement_service.py", "source_location": "L36"}, {"id": "game_movement_service_rationale_56", "label": "Initialize the movement service.          Args:             event_bus: Optional", "file_type": "rationale", "source_file": "server/game/movement_service.py", "source_location": "L56"}, {"id": "game_movement_service_rationale_83", "label": "Set the player combat service after initialization.          This allows the com", "file_type": "rationale", "source_file": "server/game/movement_service.py", "source_location": "L83"}, {"id": "game_movement_service_rationale_99", "label": "Validate movement parameters. Returns False if validation fails (same room), rai", "file_type": "rationale", "source_file": "server/game/movement_service.py", "source_location": "L99"}, {"id": "game_movement_service_rationale_139", "label": "Resolve player by ID or name and return player object and resolved ID.", "file_type": "rationale", "source_file": "server/game/movement_service.py", "source_location": "L139"}, {"id": "game_movement_service_rationale_178", "label": "Get and validate rooms for movement.", "file_type": "rationale", "source_file": "server/game/movement_service.py", "source_location": "L178"}, {"id": "game_movement_service_rationale_202", "label": "Execute the atomic room transfer.", "file_type": "rationale", "source_file": "server/game/movement_service.py", "source_location": "L202"}, {"id": "game_movement_service_rationale_213", "label": "Update player location in database.", "file_type": "rationale", "source_file": "server/game/movement_service.py", "source_location": "L213"}, {"id": "game_movement_service_rationale_222", "label": "If player exited tutorial instance (moved to fixed exit room), clear and destroy", "file_type": "rationale", "source_file": "server/game/movement_service.py", "source_location": "L222"}, {"id": "game_movement_service_rationale_241", "label": "Mark destination room as explored (non-blocking).", "file_type": "rationale", "source_file": "server/game/movement_service.py", "source_location": "L241"}, {"id": "game_movement_service_rationale_267", "label": "Handle movement errors with monitoring.", "file_type": "rationale", "source_file": "server/game/movement_service.py", "source_location": "L267"}, {"id": "game_movement_service_rationale_296", "label": "Move a player from one room to another atomically.          This operation ensur", "file_type": "rationale", "source_file": "server/game/movement_service.py", "source_location": "L296"}, {"id": "game_movement_service_rationale_389", "label": "Extract and validate player ID from player object.", "file_type": "rationale", "source_file": "server/game/movement_service.py", "source_location": "L389"}, {"id": "game_movement_service_rationale_416", "label": "Check if player is in combat (blocks movement).", "file_type": "rationale", "source_file": "server/game/movement_service.py", "source_location": "L416"}, {"id": "game_movement_service_rationale_444", "label": "Check if player posture allows movement (only standing allowed).", "file_type": "rationale", "source_file": "server/game/movement_service.py", "source_location": "L444"}, {"id": "game_movement_service_rationale_475", "label": "Validate player is in the from_room, auto-adding if database matches.", "file_type": "rationale", "source_file": "server/game/movement_service.py", "source_location": "L475"}, {"id": "game_movement_service_rationale_511", "label": "Validate that a movement operation is allowed.          Args:             player", "file_type": "rationale", "source_file": "server/game/movement_service.py", "source_location": "L511"}, {"id": "game_movement_service_rationale_575", "label": "Validate that there's a valid exit from the room to the target room.          Ar", "file_type": "rationale", "source_file": "server/game/movement_service.py", "source_location": "L575"}, {"id": "game_movement_service_rationale_621", "label": "Add a player to a room (for initial placement, teleportation, etc.).          Ar", "file_type": "rationale", "source_file": "server/game/movement_service.py", "source_location": "L621"}, {"id": "game_movement_service_rationale_702", "label": "Validate parameters for remove_player_from_room operation.", "file_type": "rationale", "source_file": "server/game/movement_service.py", "source_location": "L702"}, {"id": "game_movement_service_rationale_723", "label": "Remove a player from a room (for logout, teleportation, etc.).          Args:", "file_type": "rationale", "source_file": "server/game/movement_service.py", "source_location": "L723"}, {"id": "game_movement_service_rationale_768", "label": "Get the room ID where a player is currently located.          Args:", "file_type": "rationale", "source_file": "server/game/movement_service.py", "source_location": "L768"}, {"id": "game_movement_service_rationale_806", "label": "Get all players currently in a room.          Args:             room_id: The ID", "file_type": "rationale", "source_file": "server/game/movement_service.py", "source_location": "L806"}, {"id": "game_movement_service_rationale_830", "label": "Validate that a player is in the specified room.          Args:             play", "file_type": "rationale", "source_file": "server/game/movement_service.py", "source_location": "L830"}], "edges": [{"source": "c_projects_mythosmud_server_game_movement_service_py", "target": "threading", "relation": "imports", "context": "import", "confidence": "EXTRACTED", "source_file": "server/game/movement_service.py", "source_location": "L15", "weight": 1.0}, {"source": "c_projects_mythosmud_server_game_movement_service_py", "target": "time", "relation": "imports", "context": "import", "confidence": "EXTRACTED", "source_file": "server/game/movement_service.py", "source_location": "L16", "weight": 1.0}, {"source": "c_projects_mythosmud_server_game_movement_service_py", "target": "uuid", "relation": "imports", "context": "import", "confidence": "EXTRACTED", "source_file": "server/game/movement_service.py", "source_location": "L17", "weight": 1.0}, {"source": "c_projects_mythosmud_server_game_movement_service_py", "target": "typing", "relation": "imports_from", "context": "import", "confidence": "EXTRACTED", "source_file": "server/game/movement_service.py", "source_location": "L18", "weight": 1.0}, {"source": "c_projects_mythosmud_server_game_movement_service_py", "target": "sqlalchemy_exc", "relation": "imports_from", "context": "import", "confidence": "EXTRACTED", "source_file": "server/game/movement_service.py", "source_location": "L20", "weight": 1.0}, {"source": "c_projects_mythosmud_server_game_movement_service_py", "target": "c_projects_mythosmud_server_events_py", "relation": "imports_from", "context": "import", "confidence": "EXTRACTED", "source_file": "server/game/movement_service.py", "source_location": "L22", "weight": 1.0}, {"source": "c_projects_mythosmud_server_game_movement_service_py", "target": "c_projects_mythosmud_server_exceptions_py", "relation": "imports_from", "context": "import", "confidence": "EXTRACTED", "source_file": "server/game/movement_service.py", "source_location": "L23", "weight": 1.0}, {"source": "c_projects_mythosmud_server_game_movement_service_py", "target": "c_projects_mythosmud_server_models_room_py", "relation": "imports_from", "context": "import", "confidence": "EXTRACTED", "source_file": "server/game/movement_service.py", "source_location": "L24", "weight": 1.0}, {"source": "c_projects_mythosmud_server_game_movement_service_py", "target": "c_projects_mythosmud_server_structured_logging_enhanced_logging_config_py", "relation": "imports_from", "context": "import", "confidence": "EXTRACTED", "source_file": "server/game/movement_service.py", "source_location": "L25", "weight": 1.0}, {"source": "c_projects_mythosmud_server_game_movement_service_py", "target": "c_projects_mythosmud_server_utils_error_logging_py", "relation": "imports_from", "context": "import", "confidence": "EXTRACTED", "source_file": "server/game/movement_service.py", "source_location": "L26", "weight": 1.0}, {"source": "c_projects_mythosmud_server_game_movement_service_py", "target": "c_projects_mythosmud_server_game_movement_monitor_py", "relation": "imports_from", "context": "import", "confidence": "EXTRACTED", "source_file": "server/game/movement_service.py", "source_location": "L27", "weight": 1.0}, {"source": "c_projects_mythosmud_server_game_movement_service_py", "target": "c_projects_mythosmud_server_async_persistence_py", "relation": "imports_from", "context": "import", "confidence": "EXTRACTED", "source_file": "server/game/movement_service.py", "source_location": "L30", "weight": 1.0}, {"source": "c_projects_mythosmud_server_game_movement_service_py", "target": "c_projects_mythosmud_server_models_player_py", "relation": "imports_from", "context": "import", "confidence": "EXTRACTED", "source_file": "server/game/movement_service.py", "source_location": "L31", "weight": 1.0}, {"source": "c_projects_mythosmud_server_game_movement_service_py", "target": "c_projects_mythosmud_server_services_player_combat_service_py", "relation": "imports_from", "context": "import", "confidence": "EXTRACTED", "source_file": "server/game/movement_service.py", "source_location": "L32", "weight": 1.0}, {"source": "c_projects_mythosmud_server_game_movement_service_py", "target": "game_movement_service_movementservice", "relation": "contains", "confidence": "EXTRACTED", "source_file": "server/game/movement_service.py", "source_location": "L35", "weight": 1.0}, {"source": "game_movement_service_movementservice", "target": "game_movement_service_movementservice_init", "relation": "method", "confidence": "EXTRACTED", "source_file": "server/game/movement_service.py", "source_location": "L48", "weight": 1.0}, {"source": "game_movement_service_movementservice_init", "target": "eventbus", "relation": "references", "context": "parameter_type", "confidence": "EXTRACTED", "source_file": "server/game/movement_service.py", "source_location": "L48", "weight": 1.0}, {"source": "game_movement_service_movementservice_init", "target": "any", "relation": "references", "context": "parameter_type", "confidence": "EXTRACTED", "source_file": "server/game/movement_service.py", "source_location": "L48", "weight": 1.0}, {"source": "game_movement_service_movementservice_init", "target": "any", "relation": "references", "context": "parameter_type", "confidence": "EXTRACTED", "source_file": "server/game/movement_service.py", "source_location": "L48", "weight": 1.0}, {"source": "game_movement_service_movementservice", "target": "game_movement_service_movementservice_set_player_combat_service", "relation": "method", "confidence": "EXTRACTED", "source_file": "server/game/movement_service.py", "source_location": "L82", "weight": 1.0}, {"source": "game_movement_service_movementservice", "target": "game_movement_service_movementservice_validate_move_params", "relation": "method", "confidence": "EXTRACTED", "source_file": "server/game/movement_service.py", "source_location": "L98", "weight": 1.0}, {"source": "game_movement_service_movementservice_validate_move_params", "target": "uuid", "relation": "references", "context": "parameter_type", "confidence": "EXTRACTED", "source_file": "server/game/movement_service.py", "source_location": "L98", "weight": 1.0}, {"source": "game_movement_service_movementservice", "target": "game_movement_service_movementservice_resolve_player_for_movement", "relation": "method", "confidence": "EXTRACTED", "source_file": "server/game/movement_service.py", "source_location": "L136", "weight": 1.0}, {"source": "game_movement_service_movementservice_resolve_player_for_movement", "target": "uuid", "relation": "references", "context": "parameter_type", "confidence": "EXTRACTED", "source_file": "server/game/movement_service.py", "source_location": "L136", "weight": 1.0}, {"source": "game_movement_service_movementservice_resolve_player_for_movement", "target": "any", "relation": "references", "context": "generic_arg", "confidence": "EXTRACTED", "source_file": "server/game/movement_service.py", "source_location": "L136", "weight": 1.0}, {"source": "game_movement_service_movementservice_resolve_player_for_movement", "target": "uuid", "relation": "references", "context": "generic_arg", "confidence": "EXTRACTED", "source_file": "server/game/movement_service.py", "source_location": "L136", "weight": 1.0}, {"source": "game_movement_service_movementservice", "target": "game_movement_service_movementservice_get_rooms_for_movement", "relation": "method", "confidence": "EXTRACTED", "source_file": "server/game/movement_service.py", "source_location": "L171", "weight": 1.0}, {"source": "game_movement_service_movementservice_get_rooms_for_movement", "target": "uuid", "relation": "references", "context": "parameter_type", "confidence": "EXTRACTED", "source_file": "server/game/movement_service.py", "source_location": "L171", "weight": 1.0}, {"source": "game_movement_service_movementservice_get_rooms_for_movement", "target": "room", "relation": "references", "context": "generic_arg", "confidence": "EXTRACTED", "source_file": "server/game/movement_service.py", "source_location": "L171", "weight": 1.0}, {"source": "game_movement_service_movementservice_get_rooms_for_movement", "target": "room", "relation": "references", "context": "generic_arg", "confidence": "EXTRACTED", "source_file": "server/game/movement_service.py", "source_location": "L171", "weight": 1.0}, {"source": "game_movement_service_movementservice", "target": "game_movement_service_movementservice_execute_room_transfer", "relation": "method", "confidence": "EXTRACTED", "source_file": "server/game/movement_service.py", "source_location": "L199", "weight": 1.0}, {"source": "game_movement_service_movementservice_execute_room_transfer", "target": "room", "relation": "references", "context": "parameter_type", "confidence": "EXTRACTED", "source_file": "server/game/movement_service.py", "source_location": "L199", "weight": 1.0}, {"source": "game_movement_service_movementservice_execute_room_transfer", "target": "room", "relation": "references", "context": "parameter_type", "confidence": "EXTRACTED", "source_file": "server/game/movement_service.py", "source_location": "L199", "weight": 1.0}, {"source": "game_movement_service_movementservice_execute_room_transfer", "target": "uuid", "relation": "references", "context": "parameter_type", "confidence": "EXTRACTED", "source_file": "server/game/movement_service.py", "source_location": "L199", "weight": 1.0}, {"source": "game_movement_service_movementservice", "target": "game_movement_service_movementservice_persist_player_location", "relation": "method", "confidence": "EXTRACTED", "source_file": "server/game/movement_service.py", "source_location": "L212", "weight": 1.0}, {"source": "game_movement_service_movementservice_persist_player_location", "target": "any", "relation": "references", "context": "parameter_type", "confidence": "EXTRACTED", "source_file": "server/game/movement_service.py", "source_location": "L212", "weight": 1.0}, {"source": "game_movement_service_movementservice", "target": "game_movement_service_movementservice_handle_tutorial_exit_if_applicable", "relation": "method", "confidence": "EXTRACTED", "source_file": "server/game/movement_service.py", "source_location": "L221", "weight": 1.0}, {"source": "game_movement_service_movementservice_handle_tutorial_exit_if_applicable", "target": "any", "relation": "references", "context": "parameter_type", "confidence": "EXTRACTED", "source_file": "server/game/movement_service.py", "source_location": "L221", "weight": 1.0}, {"source": "game_movement_service_movementservice", "target": "game_movement_service_movementservice_mark_room_explored", "relation": "method", "confidence": "EXTRACTED", "source_file": "server/game/movement_service.py", "source_location": "L240", "weight": 1.0}, {"source": "game_movement_service_movementservice_mark_room_explored", "target": "uuid", "relation": "references", "context": "parameter_type", "confidence": "EXTRACTED", "source_file": "server/game/movement_service.py", "source_location": "L240", "weight": 1.0}, {"source": "game_movement_service_movementservice", "target": "game_movement_service_movementservice_handle_movement_error", "relation": "method", "confidence": "EXTRACTED", "source_file": "server/game/movement_service.py", "source_location": "L258", "weight": 1.0}, {"source": "game_movement_service_movementservice_handle_movement_error", "target": "exception", "relation": "references", "context": "parameter_type", "confidence": "EXTRACTED", "source_file": "server/game/movement_service.py", "source_location": "L258", "weight": 1.0}, {"source": "game_movement_service_movementservice_handle_movement_error", "target": "uuid", "relation": "references", "context": "parameter_type", "confidence": "EXTRACTED", "source_file": "server/game/movement_service.py", "source_location": "L258", "weight": 1.0}, {"source": "game_movement_service_movementservice", "target": "game_movement_service_movementservice_move_player", "relation": "method", "confidence": "EXTRACTED", "source_file": "server/game/movement_service.py", "source_location": "L295", "weight": 1.0}, {"source": "game_movement_service_movementservice_move_player", "target": "uuid", "relation": "references", "context": "parameter_type", "confidence": "EXTRACTED", "source_file": "server/game/movement_service.py", "source_location": "L295", "weight": 1.0}, {"source": "game_movement_service_movementservice", "target": "game_movement_service_movementservice_extract_player_id", "relation": "method", "confidence": "EXTRACTED", "source_file": "server/game/movement_service.py", "source_location": "L388", "weight": 1.0}, {"source": "game_movement_service_movementservice_extract_player_id", "target": "uuid", "relation": "references", "context": "return_type", "confidence": "EXTRACTED", "source_file": "server/game/movement_service.py", "source_location": "L388", "weight": 1.0}, {"source": "game_movement_service_movementservice", "target": "game_movement_service_movementservice_check_combat_state", "relation": "method", "confidence": "EXTRACTED", "source_file": "server/game/movement_service.py", "source_location": "L415", "weight": 1.0}, {"source": "game_movement_service_movementservice_check_combat_state", "target": "uuid", "relation": "references", "context": "parameter_type", "confidence": "EXTRACTED", "source_file": "server/game/movement_service.py", "source_location": "L415", "weight": 1.0}, {"source": "game_movement_service_movementservice", "target": "game_movement_service_movementservice_check_player_posture", "relation": "method", "confidence": "EXTRACTED", "source_file": "server/game/movement_service.py", "source_location": "L441", "weight": 1.0}, {"source": "game_movement_service_movementservice_check_player_posture", "target": "uuid", "relation": "references", "context": "parameter_type", "confidence": "EXTRACTED", "source_file": "server/game/movement_service.py", "source_location": "L441", "weight": 1.0}, {"source": "game_movement_service_movementservice", "target": "game_movement_service_movementservice_validate_player_room_membership", "relation": "method", "confidence": "EXTRACTED", "source_file": "server/game/movement_service.py", "source_location": "L474", "weight": 1.0}, {"source": "game_movement_service_movementservice_validate_player_room_membership", "target": "uuid", "relation": "references", "context": "parameter_type", "confidence": "EXTRACTED", "source_file": "server/game/movement_service.py", "source_location": "L474", "weight": 1.0}, {"source": "game_movement_service_movementservice_validate_player_room_membership", "target": "room", "relation": "references", "context": "parameter_type", "confidence": "EXTRACTED", "source_file": "server/game/movement_service.py", "source_location": "L474", "weight": 1.0}, {"source": "game_movement_service_movementservice", "target": "game_movement_service_movementservice_validate_movement", "relation": "method", "confidence": "EXTRACTED", "source_file": "server/game/movement_service.py", "source_location": "L510", "weight": 1.0}, {"source": "game_movement_service_movementservice", "target": "game_movement_service_movementservice_validate_exit", "relation": "method", "confidence": "EXTRACTED", "source_file": "server/game/movement_service.py", "source_location": "L574", "weight": 1.0}, {"source": "game_movement_service_movementservice_validate_exit", "target": "room", "relation": "references", "context": "parameter_type", "confidence": "EXTRACTED", "source_file": "server/game/movement_service.py", "source_location": "L574", "weight": 1.0}, {"source": "game_movement_service_movementservice", "target": "game_movement_service_movementservice_add_player_to_room", "relation": "method", "confidence": "EXTRACTED", "source_file": "server/game/movement_service.py", "source_location": "L620", "weight": 1.0}, {"source": "game_movement_service_movementservice_add_player_to_room", "target": "uuid", "relation": "references", "context": "parameter_type", "confidence": "EXTRACTED", "source_file": "server/game/movement_service.py", "source_location": "L620", "weight": 1.0}, {"source": "game_movement_service_movementservice", "target": "game_movement_service_movementservice_validate_remove_player_params", "relation": "method", "confidence": "EXTRACTED", "source_file": "server/game/movement_service.py", "source_location": "L701", "weight": 1.0}, {"source": "game_movement_service_movementservice_validate_remove_player_params", "target": "uuid", "relation": "references", "context": "parameter_type", "confidence": "EXTRACTED", "source_file": "server/game/movement_service.py", "source_location": "L701", "weight": 1.0}, {"source": "game_movement_service_movementservice", "target": "game_movement_service_movementservice_remove_player_from_room", "relation": "method", "confidence": "EXTRACTED", "source_file": "server/game/movement_service.py", "source_location": "L722", "weight": 1.0}, {"source": "game_movement_service_movementservice_remove_player_from_room", "target": "uuid", "relation": "references", "context": "parameter_type", "confidence": "EXTRACTED", "source_file": "server/game/movement_service.py", "source_location": "L722", "weight": 1.0}, {"source": "game_movement_service_movementservice", "target": "game_movement_service_movementservice_get_player_room", "relation": "method", "confidence": "EXTRACTED", "source_file": "server/game/movement_service.py", "source_location": "L767", "weight": 1.0}, {"source": "game_movement_service_movementservice_get_player_room", "target": "uuid", "relation": "references", "context": "parameter_type", "confidence": "EXTRACTED", "source_file": "server/game/movement_service.py", "source_location": "L767", "weight": 1.0}, {"source": "game_movement_service_movementservice", "target": "game_movement_service_movementservice_get_room_players", "relation": "method", "confidence": "EXTRACTED", "source_file": "server/game/movement_service.py", "source_location": "L805", "weight": 1.0}, {"source": "game_movement_service_movementservice", "target": "game_movement_service_movementservice_validate_player_location", "relation": "method", "confidence": "EXTRACTED", "source_file": "server/game/movement_service.py", "source_location": "L829", "weight": 1.0}, {"source": "game_movement_service_movementservice_resolve_player_for_movement", "target": "uuid", "relation": "calls", "context": "call", "confidence": "EXTRACTED", "source_file": "server/game/movement_service.py", "source_location": "L147", "weight": 1.0}, {"source": "game_movement_service_movementservice_mark_room_explored", "target": "uuid", "relation": "calls", "context": "call", "confidence": "EXTRACTED", "source_file": "server/game/movement_service.py", "source_location": "L246", "weight": 1.0}, {"source": "game_movement_service_movementservice_move_player", "target": "game_movement_service_movementservice_validate_move_params", "relation": "calls", "context": "call", "confidence": "EXTRACTED", "source_file": "server/game/movement_service.py", "source_location": "L317", "weight": 1.0}, {"source": "game_movement_service_movementservice_move_player", "target": "game_movement_service_movementservice_resolve_player_for_movement", "relation": "calls", "context": "call", "confidence": "EXTRACTED", "source_file": "server/game/movement_service.py", "source_location": "L329", "weight": 1.0}, {"source": "game_movement_service_movementservice_move_player", "target": "game_movement_service_movementservice_validate_movement", "relation": "calls", "context": "call", "confidence": "EXTRACTED", "source_file": "server/game/movement_service.py", "source_location": "L332", "weight": 1.0}, {"source": "game_movement_service_movementservice_move_player", "target": "game_movement_service_movementservice_get_rooms_for_movement", "relation": "calls", "context": "call", "confidence": "EXTRACTED", "source_file": "server/game/movement_service.py", "source_location": "L347", "weight": 1.0}, {"source": "game_movement_service_movementservice_move_player", "target": "game_movement_service_movementservice_execute_room_transfer", "relation": "calls", "context": "call", "confidence": "EXTRACTED", "source_file": "server/game/movement_service.py", "source_location": "L351", "weight": 1.0}, {"source": "game_movement_service_movementservice_move_player", "target": "game_movement_service_movementservice_persist_player_location", "relation": "calls", "context": "call", "confidence": "EXTRACTED", "source_file": "server/game/movement_service.py", "source_location": "L352", "weight": 1.0}, {"source": "game_movement_service_movementservice_move_player", "target": "game_movement_service_movementservice_handle_tutorial_exit_if_applicable", "relation": "calls", "context": "call", "confidence": "EXTRACTED", "source_file": "server/game/movement_service.py", "source_location": "L355", "weight": 1.0}, {"source": "game_movement_service_movementservice_move_player", "target": "game_movement_service_movementservice_mark_room_explored", "relation": "calls", "context": "call", "confidence": "EXTRACTED", "source_file": "server/game/movement_service.py", "source_location": "L374", "weight": 1.0}, {"source": "game_movement_service_movementservice_move_player", "target": "game_movement_service_movementservice_handle_movement_error", "relation": "calls", "context": "call", "confidence": "EXTRACTED", "source_file": "server/game/movement_service.py", "source_location": "L385", "weight": 1.0}, {"source": "game_movement_service_movementservice_extract_player_id", "target": "uuid", "relation": "calls", "context": "call", "confidence": "EXTRACTED", "source_file": "server/game/movement_service.py", "source_location": "L405", "weight": 1.0}, {"source": "game_movement_service_movementservice_validate_movement", "target": "game_movement_service_movementservice_extract_player_id", "relation": "calls", "context": "call", "confidence": "EXTRACTED", "source_file": "server/game/movement_service.py", "source_location": "L522", "weight": 1.0}, {"source": "game_movement_service_movementservice_validate_movement", "target": "game_movement_service_movementservice_check_combat_state", "relation": "calls", "context": "call", "confidence": "EXTRACTED", "source_file": "server/game/movement_service.py", "source_location": "L534", "weight": 1.0}, {"source": "game_movement_service_movementservice_validate_movement", "target": "game_movement_service_movementservice_check_player_posture", "relation": "calls", "context": "call", "confidence": "EXTRACTED", "source_file": "server/game/movement_service.py", "source_location": "L546", "weight": 1.0}, {"source": "game_movement_service_movementservice_validate_movement", "target": "game_movement_service_movementservice_validate_player_room_membership", "relation": "calls", "context": "call", "confidence": "EXTRACTED", "source_file": "server/game/movement_service.py", "source_location": "L561", "weight": 1.0}, {"source": "game_movement_service_movementservice_validate_movement", "target": "game_movement_service_movementservice_validate_exit", "relation": "calls", "context": "call", "confidence": "EXTRACTED", "source_file": "server/game/movement_service.py", "source_location": "L568", "weight": 1.0}, {"source": "game_movement_service_movementservice_add_player_to_room", "target": "uuid", "relation": "calls", "context": "call", "confidence": "EXTRACTED", "source_file": "server/game/movement_service.py", "source_location": "L669", "weight": 1.0}, {"source": "game_movement_service_movementservice_remove_player_from_room", "target": "game_movement_service_movementservice_validate_remove_player_params", "relation": "calls", "context": "call", "confidence": "EXTRACTED", "source_file": "server/game/movement_service.py", "source_location": "L733", "weight": 1.0}, {"source": "game_movement_service_movementservice_get_player_room", "target": "uuid", "relation": "calls", "context": "call", "confidence": "EXTRACTED", "source_file": "server/game/movement_service.py", "source_location": "L789", "weight": 1.0}, {"source": "game_movement_service_rationale_1", "target": "c_projects_mythosmud_server_game_movement_service_py", "relation": "rationale_for", "confidence": "EXTRACTED", "source_file": "server/game/movement_service.py", "source_location": "L1", "weight": 1.0}, {"source": "game_movement_service_rationale_36", "target": "game_movement_service_movementservice", "relation": "rationale_for", "confidence": "EXTRACTED", "source_file": "server/game/movement_service.py", "source_location": "L36", "weight": 1.0}, {"source": "game_movement_service_rationale_56", "target": "game_movement_service_movementservice_init", "relation": "rationale_for", "confidence": "EXTRACTED", "source_file": "server/game/movement_service.py", "source_location": "L56", "weight": 1.0}, {"source": "game_movement_service_rationale_83", "target": "game_movement_service_movementservice_set_player_combat_service", "relation": "rationale_for", "confidence": "EXTRACTED", "source_file": "server/game/movement_service.py", "source_location": "L83", "weight": 1.0}, {"source": "game_movement_service_rationale_99", "target": "game_movement_service_movementservice_validate_move_params", "relation": "rationale_for", "confidence": "EXTRACTED", "source_file": "server/game/movement_service.py", "source_location": "L99", "weight": 1.0}, {"source": "game_movement_service_rationale_139", "target": "game_movement_service_movementservice_resolve_player_for_movement", "relation": "rationale_for", "confidence": "EXTRACTED", "source_file": "server/game/movement_service.py", "source_location": "L139", "weight": 1.0}, {"source": "game_movement_service_rationale_178", "target": "game_movement_service_movementservice_get_rooms_for_movement", "relation": "rationale_for", "confidence": "EXTRACTED", "source_file": "server/game/movement_service.py", "source_location": "L178", "weight": 1.0}, {"source": "game_movement_service_rationale_202", "target": "game_movement_service_movementservice_execute_room_transfer", "relation": "rationale_for", "confidence": "EXTRACTED", "source_file": "server/game/movement_service.py", "source_location": "L202", "weight": 1.0}, {"source": "game_movement_service_rationale_213", "target": "game_movement_service_movementservice_persist_player_location", "relation": "rationale_for", "confidence": "EXTRACTED", "source_file": "server/game/movement_service.py", "source_location": "L213", "weight": 1.0}, {"source": "game_movement_service_rationale_222", "target": "game_movement_service_movementservice_handle_tutorial_exit_if_applicable", "relation": "rationale_for", "confidence": "EXTRACTED", "source_file": "server/game/movement_service.py", "source_location": "L222", "weight": 1.0}, {"source": "game_movement_service_rationale_241", "target": "game_movement_service_movementservice_mark_room_explored", "relation": "rationale_for", "confidence": "EXTRACTED", "source_file": "server/game/movement_service.py", "source_location": "L241", "weight": 1.0}, {"source": "game_movement_service_rationale_267", "target": "game_movement_service_movementservice_handle_movement_error", "relation": "rationale_for", "confidence": "EXTRACTED", "source_file": "server/game/movement_service.py", "source_location": "L267", "weight": 1.0}, {"source": "game_movement_service_rationale_296", "target": "game_movement_service_movementservice_move_player", "relation": "rationale_for", "confidence": "EXTRACTED", "source_file": "server/game/movement_service.py", "source_location": "L296", "weight": 1.0}, {"source": "game_movement_service_rationale_389", "target": "game_movement_service_movementservice_extract_player_id", "relation": "rationale_for", "confidence": "EXTRACTED", "source_file": "server/game/movement_service.py", "source_location": "L389", "weight": 1.0}, {"source": "game_movement_service_rationale_416", "target": "game_movement_service_movementservice_check_combat_state", "relation": "rationale_for", "confidence": "EXTRACTED", "source_file": "server/game/movement_service.py", "source_location": "L416", "weight": 1.0}, {"source": "game_movement_service_rationale_444", "target": "game_movement_service_movementservice_check_player_posture", "relation": "rationale_for", "confidence": "EXTRACTED", "source_file": "server/game/movement_service.py", "source_location": "L444", "weight": 1.0}, {"source": "game_movement_service_rationale_475", "target": "game_movement_service_movementservice_validate_player_room_membership", "relation": "rationale_for", "confidence": "EXTRACTED", "source_file": "server/game/movement_service.py", "source_location": "L475", "weight": 1.0}, {"source": "game_movement_service_rationale_511", "target": "game_movement_service_movementservice_validate_movement", "relation": "rationale_for", "confidence": "EXTRACTED", "source_file": "server/game/movement_service.py", "source_location": "L511", "weight": 1.0}, {"source": "game_movement_service_rationale_575", "target": "game_movement_service_movementservice_validate_exit", "relation": "rationale_for", "confidence": "EXTRACTED", "source_file": "server/game/movement_service.py", "source_location": "L575", "weight": 1.0}, {"source": "game_movement_service_rationale_621", "target": "game_movement_service_movementservice_add_player_to_room", "relation": "rationale_for", "confidence": "EXTRACTED", "source_file": "server/game/movement_service.py", "source_location": "L621", "weight": 1.0}, {"source": "game_movement_service_rationale_702", "target": "game_movement_service_movementservice_validate_remove_player_params", "relation": "rationale_for", "confidence": "EXTRACTED", "source_file": "server/game/movement_service.py", "source_location": "L702", "weight": 1.0}, {"source": "game_movement_service_rationale_723", "target": "game_movement_service_movementservice_remove_player_from_room", "relation": "rationale_for", "confidence": "EXTRACTED", "source_file": "server/game/movement_service.py", "source_location": "L723", "weight": 1.0}, {"source": "game_movement_service_rationale_768", "target": "game_movement_service_movementservice_get_player_room", "relation": "rationale_for", "confidence": "EXTRACTED", "source_file": "server/game/movement_service.py", "source_location": "L768", "weight": 1.0}, {"source": "game_movement_service_rationale_806", "target": "game_movement_service_movementservice_get_room_players", "relation": "rationale_for", "confidence": "EXTRACTED", "source_file": "server/game/movement_service.py", "source_location": "L806", "weight": 1.0}, {"source": "game_movement_service_rationale_830", "target": "game_movement_service_movementservice_validate_player_location", "relation": "rationale_for", "confidence": "EXTRACTED", "source_file": "server/game/movement_service.py", "source_location": "L830", "weight": 1.0}], "raw_calls": [{"caller_nid": "game_movement_service_movementservice_init", "callee": "ValueError", "is_member_call": false, "source_file": "C:\\projects\\MythosMUD\\server\\game\\movement_service.py", "source_location": "L68"}, {"caller_nid": "game_movement_service_movementservice_init", "callee": "RLock", "is_member_call": true, "source_file": "C:\\projects\\MythosMUD\\server\\game\\movement_service.py", "source_location": "L71"}, {"caller_nid": "game_movement_service_movementservice_init", "callee": "get_logger", "is_member_call": false, "source_file": "C:\\projects\\MythosMUD\\server\\game\\movement_service.py", "source_location": "L72"}, {"caller_nid": "game_movement_service_movementservice_init", "callee": "info", "is_member_call": true, "source_file": "C:\\projects\\MythosMUD\\server\\game\\movement_service.py", "source_location": "L76"}, {"caller_nid": "game_movement_service_movementservice_set_player_combat_service", "callee": "info", "is_member_call": true, "source_file": "C:\\projects\\MythosMUD\\server\\game\\movement_service.py", "source_location": "L93"}, {"caller_nid": "game_movement_service_movementservice_validate_move_params", "callee": "log_and_raise", "is_member_call": false, "source_file": "C:\\projects\\MythosMUD\\server\\game\\movement_service.py", "source_location": "L101"}, {"caller_nid": "game_movement_service_movementservice_validate_move_params", "callee": "log_and_raise", "is_member_call": false, "source_file": "C:\\projects\\MythosMUD\\server\\game\\movement_service.py", "source_location": "L110"}, {"caller_nid": "game_movement_service_movementservice_validate_move_params", "callee": "log_and_raise", "is_member_call": false, "source_file": "C:\\projects\\MythosMUD\\server\\game\\movement_service.py", "source_location": "L120"}, {"caller_nid": "game_movement_service_movementservice_validate_move_params", "callee": "warning", "is_member_call": true, "source_file": "C:\\projects\\MythosMUD\\server\\game\\movement_service.py", "source_location": "L131"}, {"caller_nid": "game_movement_service_movementservice_resolve_player_for_movement", "callee": "debug", "is_member_call": true, "source_file": "C:\\projects\\MythosMUD\\server\\game\\movement_service.py", "source_location": "L140"}, {"caller_nid": "game_movement_service_movementservice_resolve_player_for_movement", "callee": "time", "is_member_call": true, "source_file": "C:\\projects\\MythosMUD\\server\\game\\movement_service.py", "source_location": "L141"}, {"caller_nid": "game_movement_service_movementservice_resolve_player_for_movement", "callee": "get_player_by_id", "is_member_call": true, "source_file": "C:\\projects\\MythosMUD\\server\\game\\movement_service.py", "source_location": "L144"}, {"caller_nid": "game_movement_service_movementservice_resolve_player_for_movement", "callee": "get_player_by_id", "is_member_call": true, "source_file": "C:\\projects\\MythosMUD\\server\\game\\movement_service.py", "source_location": "L148"}, {"caller_nid": "game_movement_service_movementservice_resolve_player_for_movement", "callee": "get_player_by_name", "is_member_call": true, "source_file": "C:\\projects\\MythosMUD\\server\\game\\movement_service.py", "source_location": "L150"}, {"caller_nid": "game_movement_service_movementservice_resolve_player_for_movement", "callee": "info", "is_member_call": true, "source_file": "C:\\projects\\MythosMUD\\server\\game\\movement_service.py", "source_location": "L152"}, {"caller_nid": "game_movement_service_movementservice_resolve_player_for_movement", "callee": "time", "is_member_call": true, "source_file": "C:\\projects\\MythosMUD\\server\\game\\movement_service.py", "source_location": "L153"}, {"caller_nid": "game_movement_service_movementservice_resolve_player_for_movement", "callee": "error", "is_member_call": true, "source_file": "C:\\projects\\MythosMUD\\server\\game\\movement_service.py", "source_location": "L157"}, {"caller_nid": "game_movement_service_movementservice_resolve_player_for_movement", "callee": "ValidationError", "is_member_call": false, "source_file": "C:\\projects\\MythosMUD\\server\\game\\movement_service.py", "source_location": "L158"}, {"caller_nid": "game_movement_service_movementservice_resolve_player_for_movement", "callee": "info", "is_member_call": true, "source_file": "C:\\projects\\MythosMUD\\server\\game\\movement_service.py", "source_location": "L167"}, {"caller_nid": "game_movement_service_movementservice_get_rooms_for_movement", "callee": "time", "is_member_call": true, "source_file": "C:\\projects\\MythosMUD\\server\\game\\movement_service.py", "source_location": "L179"}, {"caller_nid": "game_movement_service_movementservice_get_rooms_for_movement", "callee": "get_room_by_id", "is_member_call": true, "source_file": "C:\\projects\\MythosMUD\\server\\game\\movement_service.py", "source_location": "L180"}, {"caller_nid": "game_movement_service_movementservice_get_rooms_for_movement", "callee": "get_room_by_id", "is_member_call": true, "source_file": "C:\\projects\\MythosMUD\\server\\game\\movement_service.py", "source_location": "L181"}, {"caller_nid": "game_movement_service_movementservice_get_rooms_for_movement", "callee": "time", "is_member_call": true, "source_file": "C:\\projects\\MythosMUD\\server\\game\\movement_service.py", "source_location": "L182"}, {"caller_nid": "game_movement_service_movementservice_get_rooms_for_movement", "callee": "error", "is_member_call": true, "source_file": "C:\\projects\\MythosMUD\\server\\game\\movement_service.py", "source_location": "L186"}, {"caller_nid": "game_movement_service_movementservice_get_rooms_for_movement", "callee": "ValidationError", "is_member_call": false, "source_file": "C:\\projects\\MythosMUD\\server\\game\\movement_service.py", "source_location": "L187"}, {"caller_nid": "game_movement_service_movementservice_get_rooms_for_movement", "callee": "error", "is_member_call": true, "source_file": "C:\\projects\\MythosMUD\\server\\game\\movement_service.py", "source_location": "L190"}, {"caller_nid": "game_movement_service_movementservice_get_rooms_for_movement", "callee": "ValidationError", "is_member_call": false, "source_file": "C:\\projects\\MythosMUD\\server\\game\\movement_service.py", "source_location": "L191"}, {"caller_nid": "game_movement_service_movementservice_get_rooms_for_movement", "callee": "has_player", "is_member_call": true, "source_file": "C:\\projects\\MythosMUD\\server\\game\\movement_service.py", "source_location": "L193"}, {"caller_nid": "game_movement_service_movementservice_get_rooms_for_movement", "callee": "error", "is_member_call": true, "source_file": "C:\\projects\\MythosMUD\\server\\game\\movement_service.py", "source_location": "L194"}, {"caller_nid": "game_movement_service_movementservice_get_rooms_for_movement", "callee": "ValidationError", "is_member_call": false, "source_file": "C:\\projects\\MythosMUD\\server\\game\\movement_service.py", "source_location": "L195"}, {"caller_nid": "game_movement_service_movementservice_execute_room_transfer", "callee": "info", "is_member_call": true, "source_file": "C:\\projects\\MythosMUD\\server\\game\\movement_service.py", "source_location": "L203"}, {"caller_nid": "game_movement_service_movementservice_execute_room_transfer", "callee": "time", "is_member_call": true, "source_file": "C:\\projects\\MythosMUD\\server\\game\\movement_service.py", "source_location": "L204"}, {"caller_nid": "game_movement_service_movementservice_execute_room_transfer", "callee": "debug", "is_member_call": true, "source_file": "C:\\projects\\MythosMUD\\server\\game\\movement_service.py", "source_location": "L205"}, {"caller_nid": "game_movement_service_movementservice_execute_room_transfer", "callee": "player_left", "is_member_call": true, "source_file": "C:\\projects\\MythosMUD\\server\\game\\movement_service.py", "source_location": "L206"}, {"caller_nid": "game_movement_service_movementservice_execute_room_transfer", "callee": "debug", "is_member_call": true, "source_file": "C:\\projects\\MythosMUD\\server\\game\\movement_service.py", "source_location": "L207"}, {"caller_nid": "game_movement_service_movementservice_execute_room_transfer", "callee": "player_entered", "is_member_call": true, "source_file": "C:\\projects\\MythosMUD\\server\\game\\movement_service.py", "source_location": "L208"}, {"caller_nid": "game_movement_service_movementservice_execute_room_transfer", "callee": "time", "is_member_call": true, "source_file": "C:\\projects\\MythosMUD\\server\\game\\movement_service.py", "source_location": "L209"}, {"caller_nid": "game_movement_service_movementservice_persist_player_location", "callee": "time", "is_member_call": true, "source_file": "C:\\projects\\MythosMUD\\server\\game\\movement_service.py", "source_location": "L214"}, {"caller_nid": "game_movement_service_movementservice_persist_player_location", "callee": "debug", "is_member_call": true, "source_file": "C:\\projects\\MythosMUD\\server\\game\\movement_service.py", "source_location": "L215"}, {"caller_nid": "game_movement_service_movementservice_persist_player_location", "callee": "save_player", "is_member_call": true, "source_file": "C:\\projects\\MythosMUD\\server\\game\\movement_service.py", "source_location": "L217"}, {"caller_nid": "game_movement_service_movementservice_persist_player_location", "callee": "time", "is_member_call": true, "source_file": "C:\\projects\\MythosMUD\\server\\game\\movement_service.py", "source_location": "L218"}, {"caller_nid": "game_movement_service_movementservice_handle_tutorial_exit_if_applicable", "callee": "get_exit_room_id", "is_member_call": true, "source_file": "C:\\projects\\MythosMUD\\server\\game\\movement_service.py", "source_location": "L228"}, {"caller_nid": "game_movement_service_movementservice_handle_tutorial_exit_if_applicable", "callee": "save_player", "is_member_call": true, "source_file": "C:\\projects\\MythosMUD\\server\\game\\movement_service.py", "source_location": "L232"}, {"caller_nid": "game_movement_service_movementservice_handle_tutorial_exit_if_applicable", "callee": "destroy_instance", "is_member_call": true, "source_file": "C:\\projects\\MythosMUD\\server\\game\\movement_service.py", "source_location": "L233"}, {"caller_nid": "game_movement_service_movementservice_handle_tutorial_exit_if_applicable", "callee": "info", "is_member_call": true, "source_file": "C:\\projects\\MythosMUD\\server\\game\\movement_service.py", "source_location": "L234"}, {"caller_nid": "game_movement_service_movementservice_mark_room_explored", "callee": "mark_room_as_explored_sync", "is_member_call": true, "source_file": "C:\\projects\\MythosMUD\\server\\game\\movement_service.py", "source_location": "L248"}, {"caller_nid": "game_movement_service_movementservice_mark_room_explored", "callee": "warning", "is_member_call": true, "source_file": "C:\\projects\\MythosMUD\\server\\game\\movement_service.py", "source_location": "L250"}, {"caller_nid": "game_movement_service_movementservice_handle_movement_error", "callee": "time", "is_member_call": true, "source_file": "C:\\projects\\MythosMUD\\server\\game\\movement_service.py", "source_location": "L268"}, {"caller_nid": "game_movement_service_movementservice_handle_movement_error", "callee": "get_movement_monitor", "is_member_call": false, "source_file": "C:\\projects\\MythosMUD\\server\\game\\movement_service.py", "source_location": "L270"}, {"caller_nid": "game_movement_service_movementservice_handle_movement_error", "callee": "error", "is_member_call": true, "source_file": "C:\\projects\\MythosMUD\\server\\game\\movement_service.py", "source_location": "L271"}, {"caller_nid": "game_movement_service_movementservice_handle_movement_error", "callee": "get", "is_member_call": true, "source_file": "C:\\projects\\MythosMUD\\server\\game\\movement_service.py", "source_location": "L276"}, {"caller_nid": "game_movement_service_movementservice_handle_movement_error", "callee": "get", "is_member_call": true, "source_file": "C:\\projects\\MythosMUD\\server\\game\\movement_service.py", "source_location": "L277"}, {"caller_nid": "game_movement_service_movementservice_handle_movement_error", "callee": "get", "is_member_call": true, "source_file": "C:\\projects\\MythosMUD\\server\\game\\movement_service.py", "source_location": "L278"}, {"caller_nid": "game_movement_service_movementservice_handle_movement_error", "callee": "get", "is_member_call": true, "source_file": "C:\\projects\\MythosMUD\\server\\game\\movement_service.py", "source_location": "L279"}, {"caller_nid": "game_movement_service_movementservice_handle_movement_error", "callee": "get", "is_member_call": true, "source_file": "C:\\projects\\MythosMUD\\server\\game\\movement_service.py", "source_location": "L280"}, {"caller_nid": "game_movement_service_movementservice_handle_movement_error", "callee": "get", "is_member_call": true, "source_file": "C:\\projects\\MythosMUD\\server\\game\\movement_service.py", "source_location": "L281"}, {"caller_nid": "game_movement_service_movementservice_handle_movement_error", "callee": "record_movement_attempt", "is_member_call": true, "source_file": "C:\\projects\\MythosMUD\\server\\game\\movement_service.py", "source_location": "L283"}, {"caller_nid": "game_movement_service_movementservice_handle_movement_error", "callee": "log_and_raise", "is_member_call": false, "source_file": "C:\\projects\\MythosMUD\\server\\game\\movement_service.py", "source_location": "L284"}, {"caller_nid": "game_movement_service_movementservice_move_player", "callee": "time", "is_member_call": true, "source_file": "C:\\projects\\MythosMUD\\server\\game\\movement_service.py", "source_location": "L320"}, {"caller_nid": "game_movement_service_movementservice_move_player", "callee": "get_movement_monitor", "is_member_call": false, "source_file": "C:\\projects\\MythosMUD\\server\\game\\movement_service.py", "source_location": "L321"}, {"caller_nid": "game_movement_service_movementservice_move_player", "callee": "time", "is_member_call": true, "source_file": "C:\\projects\\MythosMUD\\server\\game\\movement_service.py", "source_location": "L326"}, {"caller_nid": "game_movement_service_movementservice_move_player", "callee": "time", "is_member_call": true, "source_file": "C:\\projects\\MythosMUD\\server\\game\\movement_service.py", "source_location": "L331"}, {"caller_nid": "game_movement_service_movementservice_move_player", "callee": "time", "is_member_call": true, "source_file": "C:\\projects\\MythosMUD\\server\\game\\movement_service.py", "source_location": "L333"}, {"caller_nid": "game_movement_service_movementservice_move_player", "callee": "time", "is_member_call": true, "source_file": "C:\\projects\\MythosMUD\\server\\game\\movement_service.py", "source_location": "L335"}, {"caller_nid": "game_movement_service_movementservice_move_player", "callee": "debug", "is_member_call": true, "source_file": "C:\\projects\\MythosMUD\\server\\game\\movement_service.py", "source_location": "L336"}, {"caller_nid": "game_movement_service_movementservice_move_player", "callee": "record_movement_attempt", "is_member_call": true, "source_file": "C:\\projects\\MythosMUD\\server\\game\\movement_service.py", "source_location": "L342"}, {"caller_nid": "game_movement_service_movementservice_move_player", "callee": "time", "is_member_call": true, "source_file": "C:\\projects\\MythosMUD\\server\\game\\movement_service.py", "source_location": "L344"}, {"caller_nid": "game_movement_service_movementservice_move_player", "callee": "time", "is_member_call": true, "source_file": "C:\\projects\\MythosMUD\\server\\game\\movement_service.py", "source_location": "L357"}, {"caller_nid": "game_movement_service_movementservice_move_player", "callee": "info", "is_member_call": true, "source_file": "C:\\projects\\MythosMUD\\server\\game\\movement_service.py", "source_location": "L359"}, {"caller_nid": "game_movement_service_movementservice_move_player", "callee": "get", "is_member_call": true, "source_file": "C:\\projects\\MythosMUD\\server\\game\\movement_service.py", "source_location": "L365"}, {"caller_nid": "game_movement_service_movementservice_move_player", "callee": "get", "is_member_call": true, "source_file": "C:\\projects\\MythosMUD\\server\\game\\movement_service.py", "source_location": "L366"}, {"caller_nid": "game_movement_service_movementservice_move_player", "callee": "get", "is_member_call": true, "source_file": "C:\\projects\\MythosMUD\\server\\game\\movement_service.py", "source_location": "L367"}, {"caller_nid": "game_movement_service_movementservice_move_player", "callee": "get", "is_member_call": true, "source_file": "C:\\projects\\MythosMUD\\server\\game\\movement_service.py", "source_location": "L368"}, {"caller_nid": "game_movement_service_movementservice_move_player", "callee": "get", "is_member_call": true, "source_file": "C:\\projects\\MythosMUD\\server\\game\\movement_service.py", "source_location": "L369"}, {"caller_nid": "game_movement_service_movementservice_move_player", "callee": "get", "is_member_call": true, "source_file": "C:\\projects\\MythosMUD\\server\\game\\movement_service.py", "source_location": "L370"}, {"caller_nid": "game_movement_service_movementservice_move_player", "callee": "record_movement_attempt", "is_member_call": true, "source_file": "C:\\projects\\MythosMUD\\server\\game\\movement_service.py", "source_location": "L372"}, {"caller_nid": "game_movement_service_movementservice_move_player", "callee": "info", "is_member_call": true, "source_file": "C:\\projects\\MythosMUD\\server\\game\\movement_service.py", "source_location": "L376"}, {"caller_nid": "game_movement_service_movementservice_move_player", "callee": "time", "is_member_call": true, "source_file": "C:\\projects\\MythosMUD\\server\\game\\movement_service.py", "source_location": "L380"}, {"caller_nid": "game_movement_service_movementservice_move_player", "callee": "record_movement_attempt", "is_member_call": true, "source_file": "C:\\projects\\MythosMUD\\server\\game\\movement_service.py", "source_location": "L381"}, {"caller_nid": "game_movement_service_movementservice_move_player", "callee": "warning", "is_member_call": true, "source_file": "C:\\projects\\MythosMUD\\server\\game\\movement_service.py", "source_location": "L382"}, {"caller_nid": "game_movement_service_movementservice_extract_player_id", "callee": "error", "is_member_call": true, "source_file": "C:\\projects\\MythosMUD\\server\\game\\movement_service.py", "source_location": "L391"}, {"caller_nid": "game_movement_service_movementservice_extract_player_id", "callee": "warning", "is_member_call": true, "source_file": "C:\\projects\\MythosMUD\\server\\game\\movement_service.py", "source_location": "L398"}, {"caller_nid": "game_movement_service_movementservice_extract_player_id", "callee": "warning", "is_member_call": true, "source_file": "C:\\projects\\MythosMUD\\server\\game\\movement_service.py", "source_location": "L407"}, {"caller_nid": "game_movement_service_movementservice_check_combat_state", "callee": "warning", "is_member_call": true, "source_file": "C:\\projects\\MythosMUD\\server\\game\\movement_service.py", "source_location": "L418"}, {"caller_nid": "game_movement_service_movementservice_check_combat_state", "callee": "is_player_in_combat_sync", "is_member_call": true, "source_file": "C:\\projects\\MythosMUD\\server\\game\\movement_service.py", "source_location": "L422"}, {"caller_nid": "game_movement_service_movementservice_check_combat_state", "callee": "warning", "is_member_call": true, "source_file": "C:\\projects\\MythosMUD\\server\\game\\movement_service.py", "source_location": "L424"}, {"caller_nid": "game_movement_service_movementservice_check_combat_state", "callee": "warning", "is_member_call": true, "source_file": "C:\\projects\\MythosMUD\\server\\game\\movement_service.py", "source_location": "L433"}, {"caller_nid": "game_movement_service_movementservice_check_player_posture", "callee": "get_stats", "is_member_call": true, "source_file": "C:\\projects\\MythosMUD\\server\\game\\movement_service.py", "source_location": "L448"}, {"caller_nid": "game_movement_service_movementservice_check_player_posture", "callee": "get", "is_member_call": true, "source_file": "C:\\projects\\MythosMUD\\server\\game\\movement_service.py", "source_location": "L451"}, {"caller_nid": "game_movement_service_movementservice_check_player_posture", "callee": "lower", "is_member_call": true, "source_file": "C:\\projects\\MythosMUD\\server\\game\\movement_service.py", "source_location": "L452"}, {"caller_nid": "game_movement_service_movementservice_check_player_posture", "callee": "warning", "is_member_call": true, "source_file": "C:\\projects\\MythosMUD\\server\\game\\movement_service.py", "source_location": "L454"}, {"caller_nid": "game_movement_service_movementservice_check_player_posture", "callee": "info", "is_member_call": true, "source_file": "C:\\projects\\MythosMUD\\server\\game\\movement_service.py", "source_location": "L464"}, {"caller_nid": "game_movement_service_movementservice_validate_player_room_membership", "callee": "has_player", "is_member_call": true, "source_file": "C:\\projects\\MythosMUD\\server\\game\\movement_service.py", "source_location": "L476"}, {"caller_nid": "game_movement_service_movementservice_validate_player_room_membership", "callee": "get_player_by_id", "is_member_call": true, "source_file": "C:\\projects\\MythosMUD\\server\\game\\movement_service.py", "source_location": "L480"}, {"caller_nid": "game_movement_service_movementservice_validate_player_room_membership", "callee": "info", "is_member_call": true, "source_file": "C:\\projects\\MythosMUD\\server\\game\\movement_service.py", "source_location": "L483"}, {"caller_nid": "game_movement_service_movementservice_validate_player_room_membership", "callee": "add_player_silently", "is_member_call": true, "source_file": "C:\\projects\\MythosMUD\\server\\game\\movement_service.py", "source_location": "L488"}, {"caller_nid": "game_movement_service_movementservice_validate_player_room_membership", "callee": "error", "is_member_call": true, "source_file": "C:\\projects\\MythosMUD\\server\\game\\movement_service.py", "source_location": "L491"}, {"caller_nid": "game_movement_service_movementservice_validate_player_room_membership", "callee": "error", "is_member_call": true, "source_file": "C:\\projects\\MythosMUD\\server\\game\\movement_service.py", "source_location": "L499"}, {"caller_nid": "game_movement_service_movementservice_validate_player_room_membership", "callee": "warning", "is_member_call": true, "source_file": "C:\\projects\\MythosMUD\\server\\game\\movement_service.py", "source_location": "L502"}, {"caller_nid": "game_movement_service_movementservice_validate_movement", "callee": "info", "is_member_call": true, "source_file": "C:\\projects\\MythosMUD\\server\\game\\movement_service.py", "source_location": "L526"}, {"caller_nid": "game_movement_service_movementservice_validate_movement", "callee": "get_player_by_id", "is_member_call": true, "source_file": "C:\\projects\\MythosMUD\\server\\game\\movement_service.py", "source_location": "L541"}, {"caller_nid": "game_movement_service_movementservice_validate_movement", "callee": "get_room_by_id", "is_member_call": true, "source_file": "C:\\projects\\MythosMUD\\server\\game\\movement_service.py", "source_location": "L550"}, {"caller_nid": "game_movement_service_movementservice_validate_movement", "callee": "get_room_by_id", "is_member_call": true, "source_file": "C:\\projects\\MythosMUD\\server\\game\\movement_service.py", "source_location": "L551"}, {"caller_nid": "game_movement_service_movementservice_validate_movement", "callee": "error", "is_member_call": true, "source_file": "C:\\projects\\MythosMUD\\server\\game\\movement_service.py", "source_location": "L554"}, {"caller_nid": "game_movement_service_movementservice_validate_movement", "callee": "error", "is_member_call": true, "source_file": "C:\\projects\\MythosMUD\\server\\game\\movement_service.py", "source_location": "L558"}, {"caller_nid": "game_movement_service_movementservice_validate_movement", "callee": "has_player", "is_member_call": true, "source_file": "C:\\projects\\MythosMUD\\server\\game\\movement_service.py", "source_location": "L564"}, {"caller_nid": "game_movement_service_movementservice_validate_movement", "callee": "error", "is_member_call": true, "source_file": "C:\\projects\\MythosMUD\\server\\game\\movement_service.py", "source_location": "L565"}, {"caller_nid": "game_movement_service_movementservice_validate_movement", "callee": "error", "is_member_call": true, "source_file": "C:\\projects\\MythosMUD\\server\\game\\movement_service.py", "source_location": "L569"}, {"caller_nid": "game_movement_service_movementservice_validate_exit", "callee": "warning", "is_member_call": true, "source_file": "C:\\projects\\MythosMUD\\server\\game\\movement_service.py", "source_location": "L588"}, {"caller_nid": "game_movement_service_movementservice_validate_exit", "callee": "items", "is_member_call": true, "source_file": "C:\\projects\\MythosMUD\\server\\game\\movement_service.py", "source_location": "L592"}, {"caller_nid": "game_movement_service_movementservice_validate_exit", "callee": "debug", "is_member_call": true, "source_file": "C:\\projects\\MythosMUD\\server\\game\\movement_service.py", "source_location": "L594"}, {"caller_nid": "game_movement_service_movementservice_validate_exit", "callee": "warning", "is_member_call": true, "source_file": "C:\\projects\\MythosMUD\\server\\game\\movement_service.py", "source_location": "L599"}, {"caller_nid": "game_movement_service_movementservice_validate_exit", "callee": "keys", "is_member_call": true, "source_file": "C:\\projects\\MythosMUD\\server\\game\\movement_service.py", "source_location": "L605"}, {"caller_nid": "game_movement_service_movementservice_validate_exit", "callee": "values", "is_member_call": true, "source_file": "C:\\projects\\MythosMUD\\server\\game\\movement_service.py", "source_location": "L606"}, {"caller_nid": "game_movement_service_movementservice_validate_exit", "callee": "get_room_by_id", "is_member_call": true, "source_file": "C:\\projects\\MythosMUD\\server\\game\\movement_service.py", "source_location": "L610"}, {"caller_nid": "game_movement_service_movementservice_validate_exit", "callee": "error", "is_member_call": true, "source_file": "C:\\projects\\MythosMUD\\server\\game\\movement_service.py", "source_location": "L612"}, {"caller_nid": "game_movement_service_movementservice_add_player_to_room", "callee": "log_and_raise", "is_member_call": false, "source_file": "C:\\projects\\MythosMUD\\server\\game\\movement_service.py", "source_location": "L632"}, {"caller_nid": "game_movement_service_movementservice_add_player_to_room", "callee": "log_and_raise", "is_member_call": false, "source_file": "C:\\projects\\MythosMUD\\server\\game\\movement_service.py", "source_location": "L641"}, {"caller_nid": "game_movement_service_movementservice_add_player_to_room", "callee": "get_room_by_id", "is_member_call": true, "source_file": "C:\\projects\\MythosMUD\\server\\game\\movement_service.py", "source_location": "L652"}, {"caller_nid": "game_movement_service_movementservice_add_player_to_room", "callee": "error", "is_member_call": true, "source_file": "C:\\projects\\MythosMUD\\server\\game\\movement_service.py", "source_location": "L654"}, {"caller_nid": "game_movement_service_movementservice_add_player_to_room", "callee": "has_player", "is_member_call": true, "source_file": "C:\\projects\\MythosMUD\\server\\game\\movement_service.py", "source_location": "L658"}, {"caller_nid": "game_movement_service_movementservice_add_player_to_room", "callee": "warning", "is_member_call": true, "source_file": "C:\\projects\\MythosMUD\\server\\game\\movement_service.py", "source_location": "L659"}, {"caller_nid": "game_movement_service_movementservice_add_player_to_room", "callee": "add_player_silently", "is_member_call": true, "source_file": "C:\\projects\\MythosMUD\\server\\game\\movement_service.py", "source_location": "L663"}, {"caller_nid": "game_movement_service_movementservice_add_player_to_room", "callee": "get_player_by_id", "is_member_call": true, "source_file": "C:\\projects\\MythosMUD\\server\\game\\movement_service.py", "source_location": "L677"}, {"caller_nid": "game_movement_service_movementservice_add_player_to_room", "callee": "save_player", "is_member_call": true, "source_file": "C:\\projects\\MythosMUD\\server\\game\\movement_service.py", "source_location": "L684"}, {"caller_nid": "game_movement_service_movementservice_add_player_to_room", "callee": "info", "is_member_call": true, "source_file": "C:\\projects\\MythosMUD\\server\\game\\movement_service.py", "source_location": "L686"}, {"caller_nid": "game_movement_service_movementservice_add_player_to_room", "callee": "error", "is_member_call": true, "source_file": "C:\\projects\\MythosMUD\\server\\game\\movement_service.py", "source_location": "L690"}, {"caller_nid": "game_movement_service_movementservice_add_player_to_room", "callee": "log_and_raise", "is_member_call": false, "source_file": "C:\\projects\\MythosMUD\\server\\game\\movement_service.py", "source_location": "L691"}, {"caller_nid": "game_movement_service_movementservice_validate_remove_player_params", "callee": "log_and_raise", "is_member_call": false, "source_file": "C:\\projects\\MythosMUD\\server\\game\\movement_service.py", "source_location": "L704"}, {"caller_nid": "game_movement_service_movementservice_validate_remove_player_params", "callee": "log_and_raise", "is_member_call": false, "source_file": "C:\\projects\\MythosMUD\\server\\game\\movement_service.py", "source_location": "L713"}, {"caller_nid": "game_movement_service_movementservice_remove_player_from_room", "callee": "get_room_by_id", "is_member_call": true, "source_file": "C:\\projects\\MythosMUD\\server\\game\\movement_service.py", "source_location": "L737"}, {"caller_nid": "game_movement_service_movementservice_remove_player_from_room", "callee": "error", "is_member_call": true, "source_file": "C:\\projects\\MythosMUD\\server\\game\\movement_service.py", "source_location": "L739"}, {"caller_nid": "game_movement_service_movementservice_remove_player_from_room", "callee": "has_player", "is_member_call": true, "source_file": "C:\\projects\\MythosMUD\\server\\game\\movement_service.py", "source_location": "L743"}, {"caller_nid": "game_movement_service_movementservice_remove_player_from_room", "callee": "warning", "is_member_call": true, "source_file": "C:\\projects\\MythosMUD\\server\\game\\movement_service.py", "source_location": "L744"}, {"caller_nid": "game_movement_service_movementservice_remove_player_from_room", "callee": "player_left", "is_member_call": true, "source_file": "C:\\projects\\MythosMUD\\server\\game\\movement_service.py", "source_location": "L748"}, {"caller_nid": "game_movement_service_movementservice_remove_player_from_room", "callee": "info", "is_member_call": true, "source_file": "C:\\projects\\MythosMUD\\server\\game\\movement_service.py", "source_location": "L750"}, {"caller_nid": "game_movement_service_movementservice_remove_player_from_room", "callee": "error", "is_member_call": true, "source_file": "C:\\projects\\MythosMUD\\server\\game\\movement_service.py", "source_location": "L754"}, {"caller_nid": "game_movement_service_movementservice_remove_player_from_room", "callee": "log_and_raise", "is_member_call": false, "source_file": "C:\\projects\\MythosMUD\\server\\game\\movement_service.py", "source_location": "L757"}, {"caller_nid": "game_movement_service_movementservice_get_player_room", "callee": "log_and_raise", "is_member_call": false, "source_file": "C:\\projects\\MythosMUD\\server\\game\\movement_service.py", "source_location": "L778"}, {"caller_nid": "game_movement_service_movementservice_get_player_room", "callee": "get_player_by_id", "is_member_call": true, "source_file": "C:\\projects\\MythosMUD\\server\\game\\movement_service.py", "source_location": "L797"}, {"caller_nid": "game_movement_service_movementservice_get_player_room", "callee": "debug", "is_member_call": true, "source_file": "C:\\projects\\MythosMUD\\server\\game\\movement_service.py", "source_location": "L801"}, {"caller_nid": "game_movement_service_movementservice_get_room_players", "callee": "log_and_raise", "is_member_call": false, "source_file": "C:\\projects\\MythosMUD\\server\\game\\movement_service.py", "source_location": "L816"}, {"caller_nid": "game_movement_service_movementservice_get_room_players", "callee": "get_room_by_id", "is_member_call": true, "source_file": "C:\\projects\\MythosMUD\\server\\game\\movement_service.py", "source_location": "L823"}, {"caller_nid": "game_movement_service_movementservice_get_room_players", "callee": "get_players", "is_member_call": true, "source_file": "C:\\projects\\MythosMUD\\server\\game\\movement_service.py", "source_location": "L825"}, {"caller_nid": "game_movement_service_movementservice_validate_player_location", "callee": "log_and_raise", "is_member_call": false, "source_file": "C:\\projects\\MythosMUD\\server\\game\\movement_service.py", "source_location": "L841"}, {"caller_nid": "game_movement_service_movementservice_validate_player_location", "callee": "log_and_raise", "is_member_call": false, "source_file": "C:\\projects\\MythosMUD\\server\\game\\movement_service.py", "source_location": "L850"}, {"caller_nid": "game_movement_service_movementservice_validate_player_location", "callee": "get_room_by_id", "is_member_call": true, "source_file": "C:\\projects\\MythosMUD\\server\\game\\movement_service.py", "source_location": "L859"}, {"caller_nid": "game_movement_service_movementservice_validate_player_location", "callee": "has_player", "is_member_call": true, "source_file": "C:\\projects\\MythosMUD\\server\\game\\movement_service.py", "source_location": "L863"}]}
